{
  "slug": "masseglaeubiger",
  "title": "Massegläubiger",
  "excerpt": "Massegläubiger sind Gläubiger von Masseverbindlichkeiten, die vorrangig vor Insolvenzforderungen befriedigt werden.",
  "datePublished": "2025-11-08",
  "dateModified": "2025-12-01",
  "keywords": [
    "Massegläubiger",
    "Masseverbindlichkeiten",
    "Vorrang"
  ],
  "canonical": "/lexikon/masseglaeubiger",
  "markdown": "**Massegläubiger** haben Ansprüche aus Masseverbindlichkeiten, die nach Verfahrenseröffnung entstanden sind. Sie werden vor Insolvenzgläubigern befriedigt und haben damit einen höheren Rang in der Verteilung."
}